typer_plugins/__init__.py
typer_plugins/errors.py
typer_plugins-0.1.2.dist-info/LICENSE
typer_plugins-0.1.2.dist-info/METADATA
typer_plugins-0.1.2.dist-info/WHEEL
typer_plugins-0.1.2.dist-info/RECORD
