Metadata-Version: 2.1
Name: typer-plugins
Version: 0.1.2
Summary: Register Typer CLI applications to a main application to make it more pluggable.
Author: Brandon Spendlove
Author-email: brandon-spendlove@hotmail.co.uk
Requires-Python: >=3.10,<4.0
Classifier: Programming Language :: Python :: 3
Classifier: Programming Language :: Python :: 3.10
Classifier: Programming Language :: Python :: 3.11
Classifier: Programming Language :: Python :: 3.12
Requires-Dist: typer (>=0.9.0,<1)
